gophish/__init__.py
gophish/client.py
gophish/models.py
gophish/api/__init__.py
gophish/api/api.py
gophish/api/campaigns.py
gophish/api/groups.py
gophish/api/imap.py
gophish/api/pages.py
gophish/api/smtp.py
gophish/api/templates.py
gophish/api/webhooks.py
gophish-0.5.1.dist-info/LICENSE
gophish-0.5.1.dist-info/METADATA
gophish-0.5.1.dist-info/WHEEL
gophish-0.5.1.dist-info/top_level.txt
gophish-0.5.1.dist-info/RECORD
